liblrs_python-0.4.3.dist-info/METADATA
liblrs_python-0.4.3.dist-info/WHEEL
liblrs_python.libs/libgcc_s-39080030.so.1
liblrs_python/__init__.py
liblrs_python/__init__.pyi
liblrs_python/liblrs_python.cpython-313t-aarch64-linux-musl.so
liblrs_python/py.typed
liblrs_python-0.4.3.dist-info/RECORD
