Metadata-Version: 2.4
Name: liblrs_python
Version: 0.4.3
Requires-Dist: pip>=25.2
Requires-Python: >=3.12
